{
  "headers": {
    "Received": [
      "from ccm180.constantcontact.com (p2-pen4.ad.prodcc.net [10.252.0.104]) by p2-dmail7.ccm22.constantcontact.com (Postfix) with ESMTP id 13B3211774B2 for <7e21927b670da42e952e@cloudmailin.net>; Sun, 28 Jun 2015 13:13:13 -0400",
      "from p2-jbsvcs5193.ad.prodcc.net (p2-pen4.ad.prodcc.net [10.252.0.104]) by p2-mail125.ccm180.constantcontact.com (Postfix) with ESMTP id E61F1217818 for <7e21927b670da42e952e@cloudmailin.net>; Sun, 28 Jun 2015 13:13:05 -0400"
    ],
    "Date": "Sun, 28 Jun 2015 13:13:05 -0400",
    "From": "Thomas Beauvais <tbeauvais@constantcontact.com>",
    "Reply-To": "tbeauvais@constantcontact.com",
    "To": "7e21927b670da42e952e@cloudmailin.net",
    "Cc": "",
    "Message-ID": "<1121486561257.1113224726426.1613466778.0.281313JL.1002@scheduler.constantcontact.com>",
    "Subject": "The latest news for you",
    "Mime-Version": "1.0",
    "Content-Type": "multipart/alternative; boundary=\"----=_Part_19006659_1987528555.1435511585927\"",
    "DKIM-Signature": "v=1; q=dns/txt; a=rsa-sha256; c=relaxed/relaxed; s=1000073432; d=auth.ccsend.com; h=to:X-Feedback-ID:subject:mime-version:message-id:from:date:list-unsubscribe:reply-to; bh=WNmLP2s0Wp22qyNfJwbQTFO+XqTKIbb2PIq9hNW3RnI=; b=To6bvA3B+MGtMKLaDzSHkcBhnh6JbWGsMNbJ/7Od1Yl8iudtxCIhgHm7Z29Zeag00Dh9ILgvcsiO5smoT97/55/RpBNaI8gEAaWSakUK9xCPJraWeKKu6gfyvKgwUs4M5RjzdmWbyS5qtn0rrYp6UvVvJdGyOWILu+4+6IL9LC4=",
    "List-Unsubscribe": "http://visitor.constantcontact.com/do?p=un&m=001gyRrN-D17QUBIPuEDLRgvA%3D%3D&se=001hubkif5tvocCUXf4NvncfQ%3D%3D&t=001EkZLEx15CcE%3D&llr=97r9vymab",
    "X-Campaign-Activity-ID": "d5bd07fc-6558-410d-9940-4612fe43ca0d",
    "X-Channel-ID": "31d4dfa0-1c3f-11e5-b293-d4ae52843d28",
    "X-Mailer": "Roving Constant Contact 2012 (http://www.constantcontact.com)",
    "X-Return-Path-Hint": "A1b0H/GVYQQ2ZQEYS/kPKDQ==_1113224726426_MdTfoBw/EeWyk9SuUoQ9KA==@in.constantcontact.com",
    "X-Roving-Campaignid": "1121486561257",
    "X-Roving-Id": "1113224726426.1613466778",
    "X-Feedback-ID": "31d4dfa0-1c3f-11e5-b293-d4ae52843d28:d5bd07fc-6558-410d-9940-4612fe43ca0d:1113224726426:CTCT",
    "X-CTCT-ID": "319e1830-1c3f-11e5-b293-d4ae52843d28"
  },
  "envelope": {
    "to": "7e21927b670da42e952e@cloudmailin.net",
    "recipients": [
      "7e21927b670da42e952e@cloudmailin.net"
    ],
    "from": "A1b0H/GVYQQ2ZQEYS/kPKDQ==_1113224726426_MdTfoBw/EeWyk9SuUoQ9KA==@in.constantcontact.com",
    "helo_domain": "ccm22.constantcontact.com",
    "remote_ip": "208.75.123.130",
    "spf": {
      "result": "pass",
      "domain": "in.constantcontact.com"
    }
  },
  "plain": "Some readers see this part of your email after the subject line in the inbox. Write something brief and catchy, compelling them to open the email. Thanks For Your Purchase Care to Share Your Experience? Tell readers how their feedback will be used: to drive product improvements? Change future event schedules? Share any info that provides a level of value to the feedback. Share Feedback Name | Company | Phone | E-mail | Website STAY CONNECTED: \t \t\t \t\t\t \t\t\t\t \t\t\t\t\t \t\t\t\t \t\t\t \t\t \t \t \t\t \t\t\t \t\t\t\t \t\t\t\t\t \t\t\t\t \t\t\t \t\t \t \t \t\t \t\t\t \t\t\t\t \t\t\t\t\t \t\t\t\t \t\t\t \t\t \t Constant Contact | 123 Main | Guilford | CT | 06437 This email was sent to 7e21927b670da42e952e@cloudmailin.net by tbeauvais@constantcontact.com Update Profile/Email Address | Privacy Policy Unsubscribe",
  "html": "<!DOCTYPE html PUBLIC \"-//W3C//DTD XHTML 1.0 Transitional//EN\" \"http://www.w3.org/TR/xhtml1/DTD/xhtml1-transitional.dtd\">\n<html><head>\n  \n  <link href=\"https://static.ctctcdn.com/galileo/images/templates/Galileo-Template-Images/GalileoExternalCSS.css\" rel=\"stylesheet\" type=\"text/css\">\n  <style>\n\n    table {\n      border-collapse: collapse;\n      mso-table-lspace:0pt;\n      mso-table-rspace:0pt;\n    }\n\n    *[data-style-background-color=\"Primary\"] {\n      background-color: #bac16b;\n    }\n\n    *[data-style-background-color=\"Secondary\"] {\n      background-color: #ffffff;\n    }\n\n    *[data-style-background-color=\"Tertiary\"] {\n      background-color: #9BA621;\n    }\n\n    *[data-style-background-color=\"Accent1\"] {\n      background-color: #865fa9;\n    }\n\n    *[data-style-background-color=\"Accent2\"] {\n      background-color: #d7dbd6;\n    }\n\n    *[data-style-color=\"Primary\"] {\n      color: #bac16b;\n    }\n\n    *[data-style-color=\"Secondary\"] {\n      color: #ffffff;\n    }\n\n    *[data-style-color=\"Tertiary\"] {\n      color: #9BA621;\n    }\n\n    *[data-style-color=\"Accent1\"] {\n      color: #865fa9;\n    }\n\n    *[data-style-color=\"Accent2\"] {\n      color: #d7dbd6;\n    }\n\n    *[data-style-border-color=\"Primary\"] {\n      border-color: #bac16b;\n    }\n\n    *[data-style-border-color=\"Secondary\"] {\n      border-color: #ffffff;\n    }\n\n    *[data-style-border-color=\"Tertiary\"] {\n      border-color: #9BA621;\n    }\n\n    *[data-style-border-color=\"Accent1\"] {\n      border-color: #865fa9;\n    }\n\n    *[data-style-border-color=\"Accent2\"] {\n      border-color: #d7dbd6;\n    }\n\n    @media only screen and (max-width: 480px) {\n      table[class=\"MainWidth\"] {\n        width:100% !important;\n      }\n      td[class=\"MainCenter\"] {\n        width:100% !important;\n      }\n      td[class=\"MainSide\"] {\n        display:none !important;\n      }\n      body,td {\n        font-size: 16px;\n      }\n      table[class=\"HideInMobile\"], img[class=\"HideInMobile\"], td[class=\"HideInMobile\"] {\n        display: none !important;\n      }\n      table[class=\"MobileOuterPadding\"], td[class=\"MobileOuterPadding\"] {\n        padding: 0px 0px 0px 0px !important;\n      }\n      td[class=\"OneColumnMobile\"], table[class=\"OneColumnMobile\"] {\n        width: 100% !important;\n        display:block !important;\n      }\n      td[class=\"FooterMobile\"] {\n        padding: 0px 10px 0px 10px !important;\n      }\n      td[class=\"LogoContainer\"] {\n        padding: 10px 0px 10px 0px !important;\n      }\n      div[class=\"HeadingText\"] {\n        font-size: 26px !important;\n      }\n      div[class=\"SubheadingText\"] {\n        font-size: 18px !important;\n      }\n      div[class=\"MainTextFullWidth\"] {\n        font-size: 16px !important;\n      }\n      div[class=\"TaglineText\"] {\n        font-size: 16px !important;\n        text-align: left !important;\n      }\n      td[class=\"MainTextFullWidthTD\"] {\n        padding: 10px 20px 10px 20px !important;\n      }\n      td[class=\"FeaturePadding\"] {\n        padding: 10px 10px 10px 10px !important;\n      }\n      td[class=\"FeatureContent\"] {\n        padding: 10px 15px 10px 15px !important;\n      }\n      div[class=\"MobileFooter\"] {\n        font-size: 11px !important;\n      }\n\n      td[class=\"SocialMediaIcon\"] {\n        padding: 5px 10px 0px 10px !important;\n      }\n    }\n    @media only screen and (min-width: 601px) {\n      table[class=\"MainWidth\"] {\n        width:612px !important;\n      }\n    }\n\n  </style>\n\n</head><body align=\"center\" style=\"width:100% !important;min-width:100% !important;padding: 0px 0px 0px 0px;margin: 0px 0px 0px 0px;-webkit-text-size-adjust:100%;-ms-text-size-adjust:100%;\"><table border=\"0\" cellpadding=\"0\" cellspacing=\"0\" style=\"text-align:center\" width=\"100%\"><tr><td><img src=\"http://r20.rs6.net/on.jsp?ca=d5bd07fc-6558-410d-9940-4612fe43ca0d&a=1113224726426&r=3&o=http://ui.constantcontact.com/images/p1x1.gif&c=319e1830-1c3f-11e5-b293-d4ae52843d28&ch=31d4dfa0-1c3f-11e5-b293-d4ae52843d28\" /></td></tr><tr><td align=\"center\"><div>\n  <div align=\"center\" style=\"background-color: rgb(186, 193, 107);\">\n  \n      <table border=\"0\" cellpadding=\"0\" cellspacing=\"0\" height=\"100%\" style=\"background-color: rgb(186, 193, 107);\" width=\"100%\">\n        <tbody><tr>\n          <td align=\"center\" style=\"background-image: url(https://static.ctctcdn.com/galileo/images/templates/Galileo-Template-Images/FeedbackRequest/FeedbackRequest_BG.png); background-repeat:repeat;\" valign=\"top\">\n            <div align=\"center\" style=\"max-width:612px;margin-left:auto;margin-right:auto;padding:14px 0px 14px 0px;\">\n              <table border=\"0\" cellpadding=\"0\" cellspacing=\"0\" class=\"MainWidth\" style=\"margin-left:auto;margin-right:auto;\" width=\"100%\">\n                <tbody><tr>\n                  <td class=\"MainSide\"><img alt=\"\" border=\"0\" height=\"5\" hspace=\"0\" src=\"https://static.ctctcdn.com/letters/images/1101116784221/S.gif\" vspace=\"0\" width=\"1\"></td>\n                  <td align=\"center\" class=\"MainCenter\" style=\"padding: 15px; background-color: rgb(255, 255, 255);\" valign=\"top\" width=\"610\">\n\n                    <table border=\"0\" cellpadding=\"0\" cellspacing=\"0\" width=\"100%\">\n                      <tbody><tr>\n                        <td align=\"left\" style=\"padding: 1px; background-color: rgb(155, 166, 33);\" valign=\"top\">\n                          <table border=\"0\" cellpadding=\"0\" cellspacing=\"0\" width=\"100%\">\n                            <tbody><tr>\n                              <td align=\"center\" style=\"padding: 0px; background-color: rgb(255, 255, 255);\" valign=\"top\" width=\"100%\">\n                                <table border=\"0\" cellpadding=\"0\" cellspacing=\"0\" width=\"100%\">\n                                  <tbody><tr>\n                                    <td align=\"center\" style=\"padding: 0px 0px 0px 0px;\" valign=\"top\"><img alt=\"\" border=\"0\" hspace=\"0\" src=\"https://static.ctctcdn.com/galileo/images/templates/Galileo-Template-Images/FeedbackRequest/FeedbackRequest_CornerTL.png\" style=\"display:block;\" vspace=\"0\" width=\"41\"></td>\n                                    <td align=\"center\" height=\"1\" style=\"height:1px;line-height:1px;\" width=\"100%\"><img alt=\"\" border=\"0\" height=\"1\" hspace=\"0\" src=\"https://static.ctctcdn.com/letters/images/1101116784221/S.gif\" style=\"display: block; height:1px; width:5px;\" vspace=\"0\" width=\"5\"></td>\n                                    <td align=\"center\" style=\"padding: 0px 0px 0px 0px;\" valign=\"top\"><img alt=\"\" border=\"0\" hspace=\"0\" src=\"https://static.ctctcdn.com/galileo/images/templates/Galileo-Template-Images/FeedbackRequest/FeedbackRequest_CornerTR.png\" style=\"display:block;\" vspace=\"0\" width=\"41\"></td>\n                                  </tr>\n                                </tbody></table>\n                              </td>\n                            </tr>\n                            <tr>\n                              <td align=\"center\" style=\"padding: 0px; background-color: rgb(255, 255, 255);\" valign=\"top\" width=\"100%\">\n                                \n                                <div class=\"ui-sortable\" style=\"position: relative;\"><table border=\"0\" cellpadding=\"0\" cellspacing=\"0\" class=\"galileo-ap-layout-editor\" style=\"table-layout:fixed\" width=\"100%\">\n                                    <tbody><tr>\n                                      \n                                      <td align=\"center\" class=\"MainTextFullWidthTD\" style=\"padding: 8px 38px 9px;\" valign=\"top\" width=\"100%\">\n                                        <div style=\"font-family:Garamond,Times New Roman,Times,serif; font-size: 16px; display:block; word-wrap:break-word; width:auto; color:#865FA9;\">\n                                          <div id=\"e1a96c58-dbe5-3834-9ad7-61d84569a409\">\n                                            <div class=\"MainTextFullWidth\">\n                                              Some readers see this part of your email after the subject line in the inbox.<br>\n                                              Write something brief and catchy, compelling them to open the email.<br>\n                                            </div>\n                                          </div>\n                                        </div>\n                                      </td>\n                                      \n                                    </tr>\n                                  </tbody></table><table border=\"0\" cellpadding=\"0\" cellspacing=\"0\" class=\"galileo-ap-layout-editor\" style=\"table-layout:fixed\" width=\"100%\">\n                                    <tbody><tr>\n                                      \n                                      <td align=\"center\" style=\"padding: 13px 0px;\" valign=\"top\" width=\"100%\">\n                                        \n\n<img alt=\"\" border=\"0\" hspace=\"0\" src=\"https://static.ctctcdn.com/galileo/images/templates/Galileo-Template-Images/FeedbackRequest/FeedbackRequest_VerticalLogo.png\" style=\"display: block; height:auto !important; max-width:100% !important;\" vspace=\"0\" width=\"109\">\n                                      </td>\n                                      \n                                    </tr>\n                                  </tbody></table><table border=\"0\" cellpadding=\"0\" cellspacing=\"0\" class=\"galileo-ap-layout-editor\" width=\"100%\">\n                                    <tbody><tr>\n                                      <td align=\"center\" class=\"MainTextFullWidthTD galileo-ap-content-editor\" style=\"padding: 9px 0px; height: 1px; line-height: 1px;\" valign=\"top\" width=\"100%\">\n                                        \n                                        <table align=\"center\" border=\"0\" cellpadding=\"0\" cellspacing=\"0\" style=\"height: 1px; background-color: rgb(134, 95, 169);\" width=\"12%\">\n                                          <tbody><tr>\n                                            <td align=\"center\" height=\"1\" style=\"height: 1px; line-height: 1px; border-bottom-style: none; padding-bottom: 0px;\"><img alt=\"\" border=\"0\" height=\"1\" hspace=\"0\" src=\"https://static.ctctcdn.com/letters/images/1101116784221/S.gif\" style=\"display: block; height:1px; width:5px;\" vspace=\"0\" width=\"5\"></td>\n                                          </tr>\n                                        </tbody></table>\n                                        \n                                      </td>\n                                    </tr>\n                                  </tbody></table><table border=\"0\" cellpadding=\"0\" cellspacing=\"0\" class=\"galileo-ap-layout-editor\" style=\"table-layout:fixed\" width=\"100%\">\n                                    <tbody><tr>\n                                      \n                                      <td align=\"center\" class=\"MainTextFullWidthTD\" style=\"padding: 8px 38px 9px;\" valign=\"top\" width=\"100%\">\n                                        <div id=\"56e38fef-4a99-0b57-bde8-0cce08c31950\">\n                                          <div style=\"font-family:Garamond,Times New Roman,Times,serif; font-size: 22px; display:block; word-wrap:break-word; width:auto; color:#865FA9;\">\n                                            <div class=\"SubheadingText\">Thanks For Your Purchase<br></div>\n                                          </div>\n                                        </div>\n                                      </td>\n                                      \n                                    </tr>\n                                  </tbody></table><table border=\"0\" cellpadding=\"0\" cellspacing=\"0\" class=\"galileo-ap-layout-editor\" width=\"100%\">\n                                    <tbody><tr>\n                                      \n                                      <td align=\"center\" style=\"padding: 10px 0px;\" valign=\"top\" width=\"100%\">\n\n<img alt=\"\" border=\"0\" hspace=\"0\" src=\"https://static.ctctcdn.com/galileo/images/templates/Galileo-Template-Images/FeedbackRequest/FeedbackRequest_VerticalStockImage.jpg\" style=\"display: block; height:auto !important; max-width:100% !important;\" vspace=\"0\" width=\"340\"></td>\n                                      \n                                    </tr>\n                                  </tbody></table><table border=\"0\" cellpadding=\"0\" cellspacing=\"0\" class=\"galileo-ap-layout-editor\" style=\"table-layout:fixed\" width=\"100%\">\n                                    <tbody><tr>\n                                      \n                                      <td align=\"center\" class=\"MainTextFullWidthTD\" style=\"padding: 8px 38px 9px;\" valign=\"top\" width=\"100%\">\n                                        <div id=\"c2c9af54-83ae-5900-623a-296855b6a398\">\n                                          <div style=\"font-family: Georgia, 'Times New Roman', Times, serif; font-size: 24px; font-style: italic; display: block; word-wrap: break-word; width: auto; color: rgb(134, 95, 169);\">\n                                            <div class=\"HeadingText\">Care to Share Your Experience?<br></div>\n                                          </div>\n                                        </div>\n                                      </td>\n                                      \n                                    </tr>\n                                  </tbody></table><table border=\"0\" cellpadding=\"0\" cellspacing=\"0\" class=\"galileo-ap-layout-editor\" style=\"table-layout:fixed\" width=\"100%\">\n                                    <tbody><tr>\n                                      \n                                      <td align=\"center\" class=\"MainTextFullWidthTD\" style=\"padding: 8px 38px 9px;\" valign=\"top\" width=\"100%\">\n                                        <div id=\"f2e4e2f9-dfd0-49d1-1b61-5dfd983e787f\">\n                                          <div style=\"font-family:Garamond,Times New Roman,Times,serif; font-size: 16px; display:block; word-wrap:break-word; width:auto; color:#865FA9;\">\n                                            <div class=\"MainTextFullWidth\">\n                                              Tell readers how their feedback will be used: to drive product improvements? Change future event schedules? Share any info that provides a level of value to the feedback.<br>\n                                            </div>\n                                          </div>\n                                        </div>\n                                      </td>\n                                      \n                                    </tr>\n                                  </tbody></table><table border=\"0\" cellpadding=\"0\" cellspacing=\"0\" class=\"galileo-ap-layout-editor\" width=\"100%\">\n                                    <tbody><tr>\n                                      <td align=\"center\" class=\"MainTextFullWidthTD galileo-ap-content-editor\" style=\"padding: 8px 38px 9px 38px;\" valign=\"top\">\n                                        <table border=\"0\" cellpadding=\"0\" cellspacing=\"0\" style=\"border-radius: 6px; width: auto !important; background-color: rgb(155, 166, 33);\">\n                                          <tbody><tr>\n                                            <td align=\"center\" class=\"MainTextFullWidthTD\" style=\"padding: 9px 13px 10px 13px ;\" valign=\"top\">\n                                              <div>\n                                                <div class=\"MainTextFullWidth\"><a href=\"#\" style=\"font-family: 'Times New Roman'; font-size: 18px; color: rgb(255, 255, 255); text-decoration: none; padding: 0pt; font-style: normal; font-variant: normal; font-weight: normal; font-stretch: normal; line-height: normal;\">Share Feedback</a></div>\n                                              </div>\n                                            </td>\n                                          </tr>\n                                        </tbody></table>\n                                      </td>\n                                    </tr>\n                                  </tbody></table><table border=\"0\" cellpadding=\"0\" cellspacing=\"0\" class=\"galileo-ap-layout-editor\" width=\"100%\">\n                                    <tbody><tr>\n                                      <td align=\"center\" class=\"MainTextFullWidthTD galileo-ap-content-editor\" style=\"padding: 8px 0px; height: 1px; line-height: 1px;\" valign=\"top\" width=\"100%\">\n                                        \n                                        <table align=\"center\" border=\"0\" cellpadding=\"0\" cellspacing=\"0\" style=\"height:1px;\" width=\"100%\">\n                                          <tbody><tr>\n                                            <td align=\"center\" height=\"1\" style=\"height: 1px; line-height: 1px; border-bottom-style: none; padding-bottom: 0px;\"><img alt=\"\" border=\"0\" height=\"1\" hspace=\"0\" src=\"https://static.ctctcdn.com/letters/images/1101116784221/S.gif\" style=\"display: block; height:1px; width:5px;\" vspace=\"0\" width=\"5\"></td>\n                                          </tr>\n                                        </tbody></table>\n                                        \n                                      </td>\n                                    </tr>\n                                  </tbody></table><table border=\"0\" cellpadding=\"0\" cellspacing=\"0\" class=\"galileo-ap-layout-editor\" style=\"table-layout:fixed\" width=\"100%\">\n                                    <tbody><tr>\n                                      \n                                      <td align=\"center\" class=\"MainTextFullWidthTD\" style=\"padding: 8px 20px 9px;\" valign=\"top\" width=\"100%\">\n                                        <div id=\"aa7416fe-8409-3831-af61-f1235f4929b5\">\n                                          <div style=\"font-family: Calibri,Helvetica,Arial,sans-serif; font-size: 14px; display:block; word-wrap:break-word; width:auto; color:#865FA9;\">\n                                            <div class=\"MainTextFullWidth\">\n                                              Name | Company | Phone | <a href=\"#\" style=\"color:#9BA621;font-weight:bold;\">E-mail</a> | <a href=\"#\" style=\"color:#9BA621;font-weight:bold;\">Website</a><br>\n                                            </div>\n                                          </div>\n                                        </div>\n                                      </td>\n                                      \n                                    </tr>\n                                  </tbody></table><table border=\"0\" cellpadding=\"0\" cellspacing=\"0\" class=\"galileo-ap-layout-editor\" width=\"100%\">\n                                    <tbody><tr>\n                                      <td align=\"center\" class=\"MainTextFullWidthTD\" style=\"padding: 10px 38px;\" valign=\"top\" width=\"100%\">\n                                        \n                                        <table align=\"center\" border=\"0\" cellpadding=\"0\" cellspacing=\"0\" width=\"100%\">\n                                          <tbody><tr>\n                                            <td align=\"center\" style=\"padding: 0px 0px 10px 0px;\" valign=\"middle\">\n                                              <div>\n                                                <div style=\"font-family: Arial,Helvetica,sans-serif; font-size: 12px; color:#865FA9;\">\n                                                  <div class=\"MainTextFullWidth\">STAY CONNECTED:<br></div>\n                                                </div>\n                                              </div>\n                                            </td>\n                                          </tr>\n                                          <tr>\n                                            <td align=\"center\" valign=\"middle\">\n                                              <div class=\"icon-wrapper\"></div><table border=\"0\" cellpadding=\"0\" cellspacing=\"0\" width=\"1\">\n                                                <tbody><tr><td class=\"SocialMediaIcon\" style=\"padding: 0px 10px 0px 0px\" valign=\"top\">\n&#x9;<table cellpadding=\"0\" cellspacing=\"0\" class=\"galileo-ap-content-editor\" style=\"position: relative;\">\n&#x9;&#x9;<tbody style=\"zoom: 1;\">\n&#x9;&#x9;&#x9;<tr>\n&#x9;&#x9;&#x9;&#x9;<td align=\"center\" class=\"image-container\" valign=\"middle\">\n&#x9;&#x9;&#x9;&#x9;&#x9;<img alt=\"Facebook\" border=\"0\" class=\"social-button-icon\" height=\"22\" hspace=\"0\" name=\"facebook\" src=\"https://static.ctctcdn.com/galileo/images/templates/Galileo-SocialMedia/Facebook_22.png\" vspace=\"0\" width=\"22\">\n&#x9;&#x9;&#x9;&#x9;</td>\n&#x9;&#x9;&#x9;</tr>\n&#x9;&#x9;</tbody>\n&#x9;</table>\n\n</td><td class=\"SocialMediaIcon\" style=\"padding: 0px 10px 0px 0px\" valign=\"top\">\n&#x9;<table cellpadding=\"0\" cellspacing=\"0\" class=\"galileo-ap-content-editor\" style=\"position: relative;\">\n&#x9;&#x9;<tbody style=\"zoom: 1;\">\n&#x9;&#x9;&#x9;<tr>\n&#x9;&#x9;&#x9;&#x9;<td align=\"center\" class=\"image-container\" valign=\"middle\">\n&#x9;&#x9;&#x9;&#x9;&#x9;<img alt=\"Twitter\" border=\"0\" class=\"social-button-icon\" height=\"22\" hspace=\"0\" name=\"twitter\" src=\"https://static.ctctcdn.com/galileo/images/templates/Galileo-SocialMedia/Twitter_22.png\" vspace=\"0\" width=\"22\">\n&#x9;&#x9;&#x9;&#x9;</td>\n&#x9;&#x9;&#x9;</tr>\n&#x9;&#x9;</tbody>\n&#x9;</table>\n\n</td><td class=\"SocialMediaIcon\" style=\"padding: 0px 10px 0px 0px\" valign=\"top\">\n&#x9;<table cellpadding=\"0\" cellspacing=\"0\" class=\"galileo-ap-content-editor\" style=\"position: relative;\">\n&#x9;&#x9;<tbody style=\"zoom: 1;\">\n&#x9;&#x9;&#x9;<tr>\n&#x9;&#x9;&#x9;&#x9;<td align=\"center\" class=\"image-container\" valign=\"middle\">\n&#x9;&#x9;&#x9;&#x9;&#x9;<img alt=\"LinkedIn\" border=\"0\" class=\"social-button-icon\" height=\"22\" hspace=\"0\" name=\"linkedin\" src=\"https://static.ctctcdn.com/galileo/images/templates/Galileo-SocialMedia/LinkedIn_22.png\" vspace=\"0\" width=\"22\">\n&#x9;&#x9;&#x9;&#x9;</td>\n&#x9;&#x9;&#x9;</tr>\n&#x9;&#x9;</tbody>\n&#x9;</table>\n\n</td></tr>\n                                              </tbody></table>\n                                            </td>\n                                          </tr>\n                                        </tbody></table>\n                                        \n                                      </td>\n                                    </tr>\n                                  </tbody></table></div>\n                              </td>\n                            </tr>\n                            <tr>\n                              <td align=\"center\" style=\"padding: 0px; background-color: rgb(255, 255, 255);\" valign=\"top\" width=\"100%\">\n                                <table border=\"0\" cellpadding=\"0\" cellspacing=\"0\" width=\"100%\">\n                                  <tbody><tr>\n                                    <td align=\"center\" style=\"padding: 0px 0px 0px 0px;\" valign=\"bottom\"><img alt=\"\" border=\"0\" hspace=\"0\" src=\"https://static.ctctcdn.com/galileo/images/templates/Galileo-Template-Images/FeedbackRequest/FeedbackRequest_CornerBL.png\" style=\"display:block;\" vspace=\"0\" width=\"41\"></td>\n                                    <td align=\"center\" height=\"1\" style=\"height:1px;line-height:1px;\" width=\"100%\"><img alt=\"\" border=\"0\" height=\"1\" hspace=\"0\" src=\"https://static.ctctcdn.com/letters/images/1101116784221/S.gif\" style=\"display: block; height:1px; width:5px;\" vspace=\"0\" width=\"5\"></td>\n                                    <td align=\"center\" style=\"padding: 0px 0px 0px 0px;\" valign=\"bottom\"><img alt=\"\" border=\"0\" hspace=\"0\" src=\"https://static.ctctcdn.com/galileo/images/templates/Galileo-Template-Images/FeedbackRequest/FeedbackRequest_CornerBR.png\" style=\"display:block;\" vspace=\"0\" width=\"41\"></td>\n                                  </tr>\n                                </tbody></table>\n                              </td>\n                            </tr>\n                          </tbody></table>\n                        </td>\n                      </tr>\n                    </tbody></table>\n\n                  </td>\n                  <td class=\"MainSide\"><img alt=\"\" border=\"0\" height=\"5\" hspace=\"0\" src=\"https://static.ctctcdn.com/letters/images/1101116784221/S.gif\" vspace=\"0\" width=\"1\"></td>\n                </tr>\n              </tbody></table>\n            </div>\n          </td>\n        </tr>\n      </tbody></table>\n    </div>\n\n  </div></td></tr><tr><td></td></tr></table><div align='center' style='background-color:#F3F3F3;'>\n<table bgcolor='#f3f3f3' border='0' cellpadding='0' cellspacing='0' data-addable='false' style='background-color:#f3f3f3' width='100%'>\n<tr>\n<td align='left' valign='top'>\n<table border='0' cellpadding='0' cellspacing='0' style='background-color:#F3F3F3;' width='100%'>\n<tr>\n<td height='1' style='background-color:#B2B4B8;line-height:1px;'>\n<img height='1' src='https://static.ctctcdn.com/letters/images/1101116784221/S.gif' style='display:block;height:1px;' width='5'>\n</td>\n</tr>\n<tr>\n<td height='1' style='background-color:#B2B3B4;line-height:1px;'>\n<img height='1' src='https://static.ctctcdn.com/letters/images/1101116784221/S.gif' style='display:block;height:1px;' width='5'>\n</td>\n</tr>\n<tr>\n<td height='1' style='background-color:#B8B8B8;line-height:1px;'>\n<img height='1' src='https://static.ctctcdn.com/letters/images/1101116784221/S.gif' style='display:block;height:1px;' width='5'>\n</td>\n</tr>\n<tr>\n<td height='1' style='background-color:#C3C3C3;line-height:1px;'>\n<img height='1' src='https://static.ctctcdn.com/letters/images/1101116784221/S.gif' style='display:block;height:1px;' width='5'>\n</td>\n</tr>\n<tr>\n<td height='1' style='background-color:#D1D1D1;line-height:1px;'>\n<img height='1' src='https://static.ctctcdn.com/letters/images/1101116784221/S.gif' style='display:block;height:1px;' width='5'>\n</td>\n</tr>\n<tr>\n<td height='1' style='background-color:#DDDDDD;line-height:1px;'>\n<img height='1' src='https://static.ctctcdn.com/letters/images/1101116784221/S.gif' style='display:block;height:1px;' width='5'>\n</td>\n</tr>\n<tr>\n<td height='1' style='background-color:#E8E8E8;line-height:1px;'>\n<img height='1' src='https://static.ctctcdn.com/letters/images/1101116784221/S.gif' style='display:block;height:1px;' width='5'>\n</td>\n</tr>\n<tr>\n<td height='1' style='background-color:#EEEEEE;line-height:1px;'>\n<img height='1' src='https://static.ctctcdn.com/letters/images/1101116784221/S.gif' style='display:block;height:1px;' width='5'>\n</td>\n</tr>\n<tr>\n<td height='1' style='background-color:#F2F2F2;line-height:1px;'>\n<img height='1' src='https://static.ctctcdn.com/letters/images/1101116784221/S.gif' style='display:block;height:1px;' width='5'>\n</td>\n</tr>\n<tr>\n<td height='1' style='background-color:#F3F3F3;line-height:1px;'>\n<img height='1' src='https://static.ctctcdn.com/letters/images/1101116784221/S.gif' style='display:block;height:1px;' width='5'>\n</td>\n</tr>\n</table>\n</td>\n</tr>\n<tr>\n<td align='left' valign='top'>\n<div align='center' style='max-width:600px;margin-left:auto;margin-right:auto; background-color:#F3F3F3;'>\n<table bgcolor='#f3f3f3' border='0' cellpadding='0' cellspacing='0' class='MainWidth' style='background-color:#f3f3f3;margin-left:auto;margin-right:auto;' width='100%'>\n<tr>\n<td class='MainSide'>\n<img alt='' border='0' height='5' hspace='0' src='https://static.ctctcdn.com/letters/images/1101116784221/S.gif' vspace='0' width='1'>\n</td>\n<td align='center' class='MainCenter' valign='top' width='600'>\n<table border='0' cellpadding='0' cellspacing='0' width='100%'>\n<tr>\n<td align='left' style='color: #5b5b5b; font-size: 11px; line-height: 1.3; font-family: Arial, Helvetica, sans-serif; padding: 15px 10px 30px 10px ;' valign='top'>\n<div class='MobileFooter'>\n\nConstant Contact | 123 Main\n\n| Guilford | CT | 06437\n\n\n\n<br>\n<br>\nThis email was sent to\n<a href='mailto:7e21927b670da42e952e@cloudmailin.net' style='color: #5b5b5b;'>7e21927b670da42e952e@cloudmailin.net</a>\nby\n<a href='mailto:tbeauvais@constantcontact.com' style='color: #5b5b5b;'>tbeauvais@constantcontact.com</a>\n \n<br>\n<a href='http://visitor.constantcontact.com/do?p=oo&m=001gyRrN-D17QUBIPuEDLRgvA%3D&ch=31d4dfa0-1c3f-11e5-b293-d4ae52843d28&ca=d5bd07fc-6558-410d-9940-4612fe43ca0d' style='color: #5b5b5b;'>Update Profile/Email Address</a>\n|\n<a href='https://ui.constantcontact.com/roving/CCPrivacyPolicy.jsp' style='color: #5b5b5b;'>Privacy Policy</a>\n<br>\n<a href='http://visitor.constantcontact.com/do?p=un&m=001gyRrN-D17QUBIPuEDLRgvA%3D&ch=31d4dfa0-1c3f-11e5-b293-d4ae52843d28&ca=d5bd07fc-6558-410d-9940-4612fe43ca0d' style='color: #5b5b5b;'>Unsubscribe</a>\n\n<a href='http://visitor.constantcontact.com/do?p=un&m=001gyRrN-D17QUBIPuEDLRgvA%3D&ch=31d4dfa0-1c3f-11e5-b293-d4ae52843d28&ca=d5bd07fc-6558-410d-9940-4612fe43ca0d' style='color: #5b5b5b; text-decoration:none;' target='_blank'>\n<img alt='Safe Unsubscribe' border='0' height='12' hspace='0' src='https://static.ctctcdn.com/letters/images/SafeUnsubscribe_Footer_Logo_New.png' style='outline: none; text-decoration: none; -ms-interpolation-mode: bicubic; border-top-style: none; border-right-style: none; border-bottom-style: none; border-left-style: none;' vspace='0' width='115'>\n</a>\n<br>\n<br>\n<a href='http://www.constantcontact.com/index.jsp?cc=galileo-beta' style='color: #5b5b5b; text-decoration:none;'>\n<img alt='Trusted Email from Constant Contact - Try it FREE today.' border='0' height='33' hspace='0' src='https://static.ctctcdn.com/galileo/images/pre-template-import/immutable/CC_Footer_Logo_darktext.png' vspace='0' width='129'>\n</a>\n<br>\n</div>\n</td>\n</tr>\n</table>\n</td>\n<td class='MainSide'>\n<img alt='' border='0' height='5' hspace='0' src='https://static.ctctcdn.com/letters/images/1101116784221/S.gif' vspace='0' width='1'>\n</td>\n</tr>\n</table>\n</div>\n</td>\n</tr>\n</table>\n</div></body></html>",
  "reply_plain": null,
  "attachments": [

  ]
}